LICENSE
README.md
setup.cfg
setup.py
px_django_postgres.egg-info/PKG-INFO
px_django_postgres.egg-info/SOURCES.txt
px_django_postgres.egg-info/dependency_links.txt
px_django_postgres.egg-info/requires.txt
px_django_postgres.egg-info/top_level.txt
pxd_postgres/__init__.py
pxd_postgres/apps.py
pxd_postgres/ltree/__init__.py
pxd_postgres/ltree/apps.py
pxd_postgres/ltree/fields.py
pxd_postgres/ltree/forms.py
pxd_postgres/ltree/functions.py
pxd_postgres/ltree/lookups.py
pxd_postgres/ltree/validators.py
pxd_postgres/ltree/value.py
pxd_postgres/ltree/migrations/0001_initial.py
pxd_postgres/ltree/migrations/__init__.py